delta_change_detector/__init__.py
delta_change_detector/detector.py
delta_change_detector-0.2.5.dist-info/LICENSE
delta_change_detector-0.2.5.dist-info/METADATA
delta_change_detector-0.2.5.dist-info/WHEEL
delta_change_detector-0.2.5.dist-info/top_level.txt
delta_change_detector-0.2.5.dist-info/RECORD
