Metadata-Version: 2.1
Name: delta_change_detector
Version: 0.2.5
Summary: A package to detect changes in Delta Lake tables.
Home-page: https://github.com/npiesco/delta_change_detector
Author: Nicholas G. Piesco
Author-email: ngpiesco@gmail.com
Classifier: Programming Language :: Python :: 3
Classifier: License :: OSI Approved :: MIT License
Classifier: Operating System :: OS Independent
Requires-Python: >=3.6
License-File: LICENSE
Requires-Dist: deltalake
Requires-Dist: pyarrow
